{
    "uid": "d31fa140-06dd-450a-bafa-ceba2875ab68",
    "name": "76_Xgboost",
    "preprocessing": [
        {
            "categorical": [
                {
                    "convert_method": "categorical_to_int",
                    "convert_params": {
                        "country": {
                            "China": 0,
                            "Germany": 1,
                            "UK": 2,
                            "US": 3
                        },
                        "source": {
                            "Ads": 0,
                            "Direct": 1,
                            "Seo": 2
                        }
                    },
                    "columns": [
                        "country",
                        "source"
                    ]
                }
            ],
            "ml_task": "binary_classification",
            "params": {
                "columns_preprocessing": {
                    "country": [
                        "categorical_to_int"
                    ],
                    "source": [
                        "categorical_to_int"
                    ]
                },
                "target_preprocessing": [
                    "na_exclude"
                ],
                "ml_task": "binary_classification"
            }
        },
        {
            "categorical": [
                {
                    "convert_method": "categorical_to_int",
                    "convert_params": {
                        "country": {
                            "China": 0,
                            "Germany": 1,
                            "UK": 2,
                            "US": 3
                        },
                        "source": {
                            "Ads": 0,
                            "Direct": 1,
                            "Seo": 2
                        }
                    },
                    "columns": [
                        "country",
                        "source"
                    ]
                }
            ],
            "ml_task": "binary_classification",
            "params": {
                "columns_preprocessing": {
                    "country": [
                        "categorical_to_int"
                    ],
                    "source": [
                        "categorical_to_int"
                    ]
                },
                "target_preprocessing": [
                    "na_exclude"
                ],
                "ml_task": "binary_classification"
            }
        },
        {
            "categorical": [
                {
                    "convert_method": "categorical_to_int",
                    "convert_params": {
                        "country": {
                            "China": 0,
                            "Germany": 1,
                            "UK": 2,
                            "US": 3
                        },
                        "source": {
                            "Ads": 0,
                            "Direct": 1,
                            "Seo": 2
                        }
                    },
                    "columns": [
                        "country",
                        "source"
                    ]
                }
            ],
            "ml_task": "binary_classification",
            "params": {
                "columns_preprocessing": {
                    "country": [
                        "categorical_to_int"
                    ],
                    "source": [
                        "categorical_to_int"
                    ]
                },
                "target_preprocessing": [
                    "na_exclude"
                ],
                "ml_task": "binary_classification"
            }
        },
        {
            "categorical": [
                {
                    "convert_method": "categorical_to_int",
                    "convert_params": {
                        "country": {
                            "China": 0,
                            "Germany": 1,
                            "UK": 2,
                            "US": 3
                        },
                        "source": {
                            "Ads": 0,
                            "Direct": 1,
                            "Seo": 2
                        }
                    },
                    "columns": [
                        "country",
                        "source"
                    ]
                }
            ],
            "ml_task": "binary_classification",
            "params": {
                "columns_preprocessing": {
                    "country": [
                        "categorical_to_int"
                    ],
                    "source": [
                        "categorical_to_int"
                    ]
                },
                "target_preprocessing": [
                    "na_exclude"
                ],
                "ml_task": "binary_classification"
            }
        },
        {
            "categorical": [
                {
                    "convert_method": "categorical_to_int",
                    "convert_params": {
                        "country": {
                            "China": 0,
                            "Germany": 1,
                            "UK": 2,
                            "US": 3
                        },
                        "source": {
                            "Ads": 0,
                            "Direct": 1,
                            "Seo": 2
                        }
                    },
                    "columns": [
                        "country",
                        "source"
                    ]
                }
            ],
            "ml_task": "binary_classification",
            "params": {
                "columns_preprocessing": {
                    "country": [
                        "categorical_to_int"
                    ],
                    "source": [
                        "categorical_to_int"
                    ]
                },
                "target_preprocessing": [
                    "na_exclude"
                ],
                "ml_task": "binary_classification"
            }
        },
        {
            "categorical": [
                {
                    "convert_method": "categorical_to_int",
                    "convert_params": {
                        "country": {
                            "China": 0,
                            "Germany": 1,
                            "UK": 2,
                            "US": 3
                        },
                        "source": {
                            "Ads": 0,
                            "Direct": 1,
                            "Seo": 2
                        }
                    },
                    "columns": [
                        "country",
                        "source"
                    ]
                }
            ],
            "ml_task": "binary_classification",
            "params": {
                "columns_preprocessing": {
                    "country": [
                        "categorical_to_int"
                    ],
                    "source": [
                        "categorical_to_int"
                    ]
                },
                "target_preprocessing": [
                    "na_exclude"
                ],
                "ml_task": "binary_classification"
            }
        },
        {
            "categorical": [
                {
                    "convert_method": "categorical_to_int",
                    "convert_params": {
                        "country": {
                            "China": 0,
                            "Germany": 1,
                            "UK": 2,
                            "US": 3
                        },
                        "source": {
                            "Ads": 0,
                            "Direct": 1,
                            "Seo": 2
                        }
                    },
                    "columns": [
                        "country",
                        "source"
                    ]
                }
            ],
            "ml_task": "binary_classification",
            "params": {
                "columns_preprocessing": {
                    "country": [
                        "categorical_to_int"
                    ],
                    "source": [
                        "categorical_to_int"
                    ]
                },
                "target_preprocessing": [
                    "na_exclude"
                ],
                "ml_task": "binary_classification"
            }
        },
        {
            "categorical": [
                {
                    "convert_method": "categorical_to_int",
                    "convert_params": {
                        "country": {
                            "China": 0,
                            "Germany": 1,
                            "UK": 2,
                            "US": 3
                        },
                        "source": {
                            "Ads": 0,
                            "Direct": 1,
                            "Seo": 2
                        }
                    },
                    "columns": [
                        "country",
                        "source"
                    ]
                }
            ],
            "ml_task": "binary_classification",
            "params": {
                "columns_preprocessing": {
                    "country": [
                        "categorical_to_int"
                    ],
                    "source": [
                        "categorical_to_int"
                    ]
                },
                "target_preprocessing": [
                    "na_exclude"
                ],
                "ml_task": "binary_classification"
            }
        },
        {
            "categorical": [
                {
                    "convert_method": "categorical_to_int",
                    "convert_params": {
                        "country": {
                            "China": 0,
                            "Germany": 1,
                            "UK": 2,
                            "US": 3
                        },
                        "source": {
                            "Ads": 0,
                            "Direct": 1,
                            "Seo": 2
                        }
                    },
                    "columns": [
                        "country",
                        "source"
                    ]
                }
            ],
            "ml_task": "binary_classification",
            "params": {
                "columns_preprocessing": {
                    "country": [
                        "categorical_to_int"
                    ],
                    "source": [
                        "categorical_to_int"
                    ]
                },
                "target_preprocessing": [
                    "na_exclude"
                ],
                "ml_task": "binary_classification"
            }
        },
        {
            "categorical": [
                {
                    "convert_method": "categorical_to_int",
                    "convert_params": {
                        "country": {
                            "China": 0,
                            "Germany": 1,
                            "UK": 2,
                            "US": 3
                        },
                        "source": {
                            "Ads": 0,
                            "Direct": 1,
                            "Seo": 2
                        }
                    },
                    "columns": [
                        "country",
                        "source"
                    ]
                }
            ],
            "ml_task": "binary_classification",
            "params": {
                "columns_preprocessing": {
                    "country": [
                        "categorical_to_int"
                    ],
                    "source": [
                        "categorical_to_int"
                    ]
                },
                "target_preprocessing": [
                    "na_exclude"
                ],
                "ml_task": "binary_classification"
            }
        }
    ],
    "learners": [
        {
            "library_version": "1.7.1",
            "algorithm_name": "Extreme Gradient Boosting",
            "algorithm_short_name": "Xgboost",
            "uid": "55ccdbdd-6c68-49cb-a485-efd9bad402e2",
            "params": {
                "model_type": "Xgboost",
                "ml_task": "binary_classification",
                "n_jobs": -1,
                "seed": 1235,
                "objective": "binary:logistic",
                "eta": 0.075,
                "max_depth": 8,
                "min_child_weight": 1,
                "subsample": 1.0,
                "colsample_bytree": 1.0,
                "eval_metric": "f1",
                "explain_level": 0
            },
            "name": "learner_fold_0",
            "best_ntree_limit": 30
        },
        {
            "library_version": "1.7.1",
            "algorithm_name": "Extreme Gradient Boosting",
            "algorithm_short_name": "Xgboost",
            "uid": "39a35c5f-6622-45d1-8f8f-18ec876b0365",
            "params": {
                "model_type": "Xgboost",
                "ml_task": "binary_classification",
                "n_jobs": -1,
                "seed": 1235,
                "objective": "binary:logistic",
                "eta": 0.075,
                "max_depth": 8,
                "min_child_weight": 1,
                "subsample": 1.0,
                "colsample_bytree": 1.0,
                "eval_metric": "f1",
                "explain_level": 0
            },
            "name": "learner_fold_1",
            "best_ntree_limit": 117
        },
        {
            "library_version": "1.7.1",
            "algorithm_name": "Extreme Gradient Boosting",
            "algorithm_short_name": "Xgboost",
            "uid": "976d1c30-4618-4032-99a8-e2c8a7cc8041",
            "params": {
                "model_type": "Xgboost",
                "ml_task": "binary_classification",
                "n_jobs": -1,
                "seed": 1235,
                "objective": "binary:logistic",
                "eta": 0.075,
                "max_depth": 8,
                "min_child_weight": 1,
                "subsample": 1.0,
                "colsample_bytree": 1.0,
                "eval_metric": "f1",
                "explain_level": 0
            },
            "name": "learner_fold_2",
            "best_ntree_limit": 100
        },
        {
            "library_version": "1.7.1",
            "algorithm_name": "Extreme Gradient Boosting",
            "algorithm_short_name": "Xgboost",
            "uid": "5f7296ff-f6e2-4f7b-a7b5-da4863d4403d",
            "params": {
                "model_type": "Xgboost",
                "ml_task": "binary_classification",
                "n_jobs": -1,
                "seed": 1235,
                "objective": "binary:logistic",
                "eta": 0.075,
                "max_depth": 8,
                "min_child_weight": 1,
                "subsample": 1.0,
                "colsample_bytree": 1.0,
                "eval_metric": "f1",
                "explain_level": 0
            },
            "name": "learner_fold_3",
            "best_ntree_limit": 137
        },
        {
            "library_version": "1.7.1",
            "algorithm_name": "Extreme Gradient Boosting",
            "algorithm_short_name": "Xgboost",
            "uid": "f39b326c-ea8d-470f-816f-833493e9ed00",
            "params": {
                "model_type": "Xgboost",
                "ml_task": "binary_classification",
                "n_jobs": -1,
                "seed": 1235,
                "objective": "binary:logistic",
                "eta": 0.075,
                "max_depth": 8,
                "min_child_weight": 1,
                "subsample": 1.0,
                "colsample_bytree": 1.0,
                "eval_metric": "f1",
                "explain_level": 0
            },
            "name": "learner_fold_4",
            "best_ntree_limit": 146
        },
        {
            "library_version": "1.7.1",
            "algorithm_name": "Extreme Gradient Boosting",
            "algorithm_short_name": "Xgboost",
            "uid": "8ed0cb93-6c04-4683-aa74-fd93ae787963",
            "params": {
                "model_type": "Xgboost",
                "ml_task": "binary_classification",
                "n_jobs": -1,
                "seed": 1235,
                "objective": "binary:logistic",
                "eta": 0.075,
                "max_depth": 8,
                "min_child_weight": 1,
                "subsample": 1.0,
                "colsample_bytree": 1.0,
                "eval_metric": "f1",
                "explain_level": 0
            },
            "name": "learner_fold_5",
            "best_ntree_limit": 85
        },
        {
            "library_version": "1.7.1",
            "algorithm_name": "Extreme Gradient Boosting",
            "algorithm_short_name": "Xgboost",
            "uid": "fa7df926-bde5-4de6-ae99-2602f6dafb93",
            "params": {
                "model_type": "Xgboost",
                "ml_task": "binary_classification",
                "n_jobs": -1,
                "seed": 1235,
                "objective": "binary:logistic",
                "eta": 0.075,
                "max_depth": 8,
                "min_child_weight": 1,
                "subsample": 1.0,
                "colsample_bytree": 1.0,
                "eval_metric": "f1",
                "explain_level": 0
            },
            "name": "learner_fold_6",
            "best_ntree_limit": 66
        },
        {
            "library_version": "1.7.1",
            "algorithm_name": "Extreme Gradient Boosting",
            "algorithm_short_name": "Xgboost",
            "uid": "4f461c36-8ca3-44c5-bd52-55f5f9d87d45",
            "params": {
                "model_type": "Xgboost",
                "ml_task": "binary_classification",
                "n_jobs": -1,
                "seed": 1235,
                "objective": "binary:logistic",
                "eta": 0.075,
                "max_depth": 8,
                "min_child_weight": 1,
                "subsample": 1.0,
                "colsample_bytree": 1.0,
                "eval_metric": "f1",
                "explain_level": 0
            },
            "name": "learner_fold_7",
            "best_ntree_limit": 112
        },
        {
            "library_version": "1.7.1",
            "algorithm_name": "Extreme Gradient Boosting",
            "algorithm_short_name": "Xgboost",
            "uid": "e224f06c-b33c-4605-b58c-986615497333",
            "params": {
                "model_type": "Xgboost",
                "ml_task": "binary_classification",
                "n_jobs": -1,
                "seed": 1235,
                "objective": "binary:logistic",
                "eta": 0.075,
                "max_depth": 8,
                "min_child_weight": 1,
                "subsample": 1.0,
                "colsample_bytree": 1.0,
                "eval_metric": "f1",
                "explain_level": 0
            },
            "name": "learner_fold_8",
            "best_ntree_limit": 152
        },
        {
            "library_version": "1.7.1",
            "algorithm_name": "Extreme Gradient Boosting",
            "algorithm_short_name": "Xgboost",
            "uid": "3921d9b0-b46a-4b7f-a950-caf03d0d16ba",
            "params": {
                "model_type": "Xgboost",
                "ml_task": "binary_classification",
                "n_jobs": -1,
                "seed": 1235,
                "objective": "binary:logistic",
                "eta": 0.075,
                "max_depth": 8,
                "min_child_weight": 1,
                "subsample": 1.0,
                "colsample_bytree": 1.0,
                "eval_metric": "f1",
                "explain_level": 0
            },
            "name": "learner_fold_9",
            "best_ntree_limit": 66
        }
    ],
    "params": {
        "additional": {
            "max_rounds": 10000,
            "early_stopping_rounds": 50,
            "max_rows_limit": null,
            "max_cols_limit": null
        },
        "preprocessing": {
            "columns_preprocessing": {
                "country": [
                    "categorical_to_int"
                ],
                "source": [
                    "categorical_to_int"
                ]
            },
            "target_preprocessing": [
                "na_exclude"
            ],
            "ml_task": "binary_classification"
        },
        "validation_strategy": {
            "validation_type": "kfold",
            "shuffle": true,
            "stratify": true,
            "X_path": "AutoML_4\\X.data",
            "y_path": "AutoML_4\\y.data",
            "results_path": "AutoML_4",
            "k_folds": 10
        },
        "learner": {
            "model_type": "Xgboost",
            "ml_task": "binary_classification",
            "n_jobs": -1,
            "seed": 1235,
            "objective": "binary:logistic",
            "eta": 0.075,
            "max_depth": 8,
            "min_child_weight": 1,
            "subsample": 1.0,
            "colsample_bytree": 1.0,
            "eval_metric": "f1",
            "explain_level": 0
        },
        "automl_random_state": 1234,
        "ml_task": "binary_classification",
        "explain_level": 0,
        "name": "76_Xgboost",
        "status": "initialized",
        "final_loss": null,
        "train_time": null,
        "data_type": "original",
        "max_time_for_learner": 216.0
    },
    "saved": [
        "76_Xgboost\\learner_fold_0.xgboost",
        "76_Xgboost\\learner_fold_1.xgboost",
        "76_Xgboost\\learner_fold_2.xgboost",
        "76_Xgboost\\learner_fold_3.xgboost",
        "76_Xgboost\\learner_fold_4.xgboost",
        "76_Xgboost\\learner_fold_5.xgboost",
        "76_Xgboost\\learner_fold_6.xgboost",
        "76_Xgboost\\learner_fold_7.xgboost",
        "76_Xgboost\\learner_fold_8.xgboost",
        "76_Xgboost\\learner_fold_9.xgboost"
    ],
    "predictions_fname": "76_Xgboost\\predictions_out_of_folds.csv",
    "metric_name": "f1",
    "final_loss": -0.7649099399599733,
    "train_time": 235.41536688804626,
    "is_stacked": false,
    "threshold": 0.4889695942401886
}